llama_index/readers/chroma/__init__.py
llama_index/readers/chroma/base.py
llama_index_readers_chroma-0.4.1.dist-info/METADATA
llama_index_readers_chroma-0.4.1.dist-info/WHEEL
llama_index_readers_chroma-0.4.1.dist-info/licenses/LICENSE
llama_index_readers_chroma-0.4.1.dist-info/RECORD
