Metadata-Version: 2.4
Name: llama-index-readers-chroma
Version: 0.4.1
Summary: llama-index readers chroma integration
Author-email: Your Name <you@example.com>
Maintainer: atroyn
License-Expression: MIT
License-File: LICENSE
Requires-Python: <4.0,>=3.10
Requires-Dist: chromadb<0.5,>=0.4.22
Requires-Dist: llama-index-core<0.15,>=0.13.0
